StrideModbusDriver/StrideClient.py
StrideModbusDriver/__init__.py
StrideModbusDriver-0.11.0.dist-info/METADATA
StrideModbusDriver-0.11.0.dist-info/WHEEL
StrideModbusDriver-0.11.0.dist-info/top_level.txt
StrideModbusDriver-0.11.0.dist-info/RECORD
